<?xml version="1.0" encoding="UTF-8"?>
<!DOCTYPE struts PUBLIC
    "-//Apache Software Foundation//DTD Struts Configuration 2.0//EN"
    "http://struts.apache.org/dtds/struts-2.0.dtd">
<struts>
	<constant name="struts.objectFactory" value="struts" />
	<constant name="struts.action.extension" value="action" />
	<!-- package必须继承 jasperreports-default-->
	<package name="default" extends="jasperreports-default">
		<action name="jasperAction" class="com.hrl.jr.ReportAction">
		    <!-- 返回类型必须是jasper，这是固定写法 -->
			<result name="success" type="jasper">
			   <!-- 配置报表属性 -->
			   <param name="location">/report/order.jasper</param>
			   <param name="format">HTML</param>
			   <param name="connection">conn</param>
			</result>
		</action>
	</package>
</struts>
